LICENSE
MANIFEST.in
README.rst
setup.py
upload.bat
radware_os_lb_v2_ocata/__init__.py
radware_os_lb_v2_ocata/base_v2_driver.py
radware_os_lb_v2_ocata/exceptions.py
radware_os_lb_v2_ocata/my_driver.py
radware_os_lb_v2_ocata/rest_client.py
radware_os_lb_v2_ocata/v2_driver.py
radware_os_lb_v2_ocata.egg-info/PKG-INFO
radware_os_lb_v2_ocata.egg-info/SOURCES.txt
radware_os_lb_v2_ocata.egg-info/dependency_links.txt
radware_os_lb_v2_ocata.egg-info/not-zip-safe
radware_os_lb_v2_ocata.egg-info/top_level.txt