Metadata-Version: 1.1
Name: radware-os-lb-v2-ocata
Version: 4.2.1-1
Summary: Radware LBaaS v2 driver for Openstack Ocata
Home-page: https://pypi.python.org/pypi/radware_os_lb_v2_ocata
Author: Evgeny Fedoruk, Radware
Author-email: evgenyf@radware.com
License: UNKNOWN
Keywords: openstack,radware,lbaasv2
Platform: UNKNOWN
Classifier: Environment :: OpenStack
Classifier: Intended Audience :: Information Technology
Classifier: Intended Audience :: System Administrators
Classifier: License :: OSI Approved :: Apache Software License
Classifier: Operating System :: POSIX :: Linux
Classifier: Programming Language :: Python :: 2.7
